[
    {
        "coolingdegreedays": "11",
        "coolingdegreedaysnormal": "3",
        "date": {
            "hour": "12",
            "mday": "26",
            "min": "00",
            "mon": "05",
            "pretty": "12:00 PM EDT on May 26, 2014",
            "tzname": "America/New_York",
            "year": "2014"
        },
        "fog": "0",
        "gdegreedays": "25",
        "hail": "0",
        "heatingdegreedays": "0",
        "heatingdegreedaysnormal": "3",
        "humidity": "",
        "maxdewpti": "52",
        "maxdewptm": "11",
        "maxhumidity": "49",
        "maxpressurei": "30.05",
        "maxpressurem": "1017",
        "maxtempi": "86",
        "maxtempm": "30",
        "maxvisi": "10",
        "maxvism": "16",
        "maxwspdi": "14",
        "maxwspdm": "23",
        "meandewpti": "48",
        "meandewptm": "9",
        "meanpressurei": "29.98",
        "meanpressurem": "1015",
        "meantempi": "76",
        "meantempm": "24",
        "meanvisi": "10",
        "meanvism": "16",
        "meanwdird": "264",
        "meanwdire": "",
        "meanwindspdi": "5",
        "meanwindspdm": "8",
        "mindewpti": "44",
        "mindewptm": "7",
        "minhumidity": "25",
        "minpressurei": "29.89",
        "minpressurem": "1012",
        "mintempi": "66",
        "mintempm": "19",
        "minvisi": "10",
        "minvism": "16",
        "minwspdi": "0",
        "minwspdm": "0",
        "monthtodatecoolingdegreedays": "40",
        "monthtodatecoolingdegreedaysnormal": "41",
        "monthtodateheatingdegreedays": "61",
        "monthtodateheatingdegreedaysnormal": "127",
        "monthtodatesnowfalli": "0.00",
        "monthtodatesnowfallm": "0.00",
        "precipi": "0.00",
        "precipm": "0.00",
        "precipsource": "",
        "rain": "0",
        "since1jancoolingdegreedays": "44",
        "since1jancoolingdegreedaysnormal": "53",
        "since1julheatingdegreedays": "4950",
        "since1julheatingdegreedaysnormal": "4720",
        "since1julsnowfalli": "57.40",
        "since1julsnowfallm": "145.80",
        "since1sepcoolingdegreedays": "",
        "since1sepcoolingdegreedaysnormal": "",
        "since1sepheatingdegreedays": "",
        "since1sepheatingdegreedaysnormal": "",
        "snow": "0",
        "snowdepthi": "0.00",
        "snowdepthm": "0.00",
        "snowfalli": "0.00",
        "snowfallm": "0.00",
        "thunder": "0",
        "tornado": "0"
    }
]