[
    {
        "coolingdegreedays": "0",
        "coolingdegreedaysnormal": "0",
        "date": {
            "hour": "12",
            "mday": "26",
            "min": "00",
            "mon": "11",
            "pretty": "12:00 PM EST on November 26, 2014",
            "tzname": "America/New_York",
            "year": "2014"
        },
        "fog": "0",
        "gdegreedays": "0",
        "hail": "0",
        "heatingdegreedays": "22",
        "heatingdegreedaysnormal": "21",
        "humidity": "",
        "maxdewpti": "35",
        "maxdewptm": "2",
        "maxhumidity": "92",
        "maxpressurei": "30.20",
        "maxpressurem": "1023",
        "maxtempi": "51",
        "maxtempm": "11",
        "maxvisi": "10",
        "maxvism": "16",
        "maxwspdi": "18",
        "maxwspdm": "29",
        "meandewpti": "32",
        "meandewptm": "0",
        "meanpressurei": "29.98",
        "meanpressurem": "1015",
        "meantempi": "43",
        "meantempm": "6",
        "meanvisi": "5",
        "meanvism": "8",
        "meanwdird": "32",
        "meanwdire": "",
        "meanwindspdi": "9",
        "meanwindspdm": "14",
        "mindewpti": "27",
        "mindewptm": "-3",
        "minhumidity": "38",
        "minpressurei": "29.78",
        "minpressurem": "1008",
        "mintempi": "34",
        "mintempm": "1",
        "minvisi": "1",
        "minvism": "1",
        "minwspdi": "4",
        "minwspdm": "6",
        "monthtodatecoolingdegreedays": "0",
        "monthtodatecoolingdegreedaysnormal": "0",
        "monthtodateheatingdegreedays": "479",
        "monthtodateheatingdegreedaysnormal": "433",
        "monthtodatesnowfalli": "0.20",
        "monthtodatesnowfallm": "0.51",
        "precipi": "1.24",
        "precipm": "31.50",
        "precipsource": "",
        "rain": "1",
        "since1jancoolingdegreedays": "1128",
        "since1jancoolingdegreedaysnormal": "1104",
        "since1julheatingdegreedays": "680",
        "since1julheatingdegreedaysnormal": "746",
        "since1julsnowfalli": "0.20",
        "since1julsnowfallm": "0.51",
        "since1sepcoolingdegreedays": "190",
        "since1sepcoolingdegreedaysnormal": "150",
        "since1sepheatingdegreedays": "680",
        "since1sepheatingdegreedaysnormal": "744",
        "snow": "1",
        "snowdepthi": "0.00",
        "snowdepthm": "0.00",
        "snowfalli": "0.20",
        "snowfallm": "0.51",
        "thunder": "0",
        "tornado": "0"
    }
]