[
    {
        "coolingdegreedays": "20",
        "coolingdegreedaysnormal": "",
        "date": {
            "hour": "12",
            "mday": "24",
            "min": "00",
            "mon": "07",
            "pretty": "12:00 PM EDT on July 24, 2014",
            "tzname": "America/New_York",
            "year": "2014"
        },
        "fog": "0",
        "gdegreedays": "34",
        "hail": "0",
        "heatingdegreedays": "0",
        "heatingdegreedaysnormal": "",
        "humidity": "",
        "maxdewpti": "78",
        "maxdewptm": "26",
        "maxhumidity": "94",
        "maxpressurei": "30.08",
        "maxpressurem": "1019",
        "maxtempi": "93",
        "maxtempm": "34",
        "maxvisi": "10",
        "maxvism": "16",
        "maxwspdi": "18",
        "maxwspdm": "29",
        "meandewpti": "75",
        "meandewptm": "24",
        "meanpressurei": "30.03",
        "meanpressurem": "1017",
        "meantempi": "84",
        "meantempm": "29",
        "meanvisi": "9",
        "meanvism": "15",
        "meanwdird": "213",
        "meanwdire": "",
        "meanwindspdi": "5",
        "meanwindspdm": "8",
        "mindewpti": "73",
        "mindewptm": "23",
        "minhumidity": "55",
        "minpressurei": "29.97",
        "minpressurem": "1015",
        "mintempi": "78",
        "mintempm": "26",
        "minvisi": "1",
        "minvism": "2",
        "minwspdi": "0",
        "minwspdm": "0",
        "monthtodatecoolingdegreedays": "",
        "monthtodatecoolingdegreedaysnormal": "",
        "monthtodateheatingdegreedays": "",
        "monthtodateheatingdegreedaysnormal": "",
        "monthtodatesnowfalli": "",
        "monthtodatesnowfallm": "",
        "precipi": "0.15",
        "precipm": "3.81",
        "precipsource": "",
        "rain": "1",
        "since1jancoolingdegreedays": "",
        "since1jancoolingdegreedaysnormal": "",
        "since1julheatingdegreedays": "",
        "since1julheatingdegreedaysnormal": "",
        "since1julsnowfalli": "",
        "since1julsnowfallm": "",
        "since1sepcoolingdegreedays": "",
        "since1sepcoolingdegreedaysnormal": "",
        "since1sepheatingdegreedays": "",
        "since1sepheatingdegreedaysnormal": "",
        "snow": "0",
        "snowdepthi": "",
        "snowdepthm": "",
        "snowfalli": "0.00",
        "snowfallm": "0.00",
        "thunder": "1",
        "tornado": "0"
    }
]