[
    {
        "coolingdegreedays": "8",
        "coolingdegreedaysnormal": "6",
        "date": {
            "hour": "12",
            "mday": "25",
            "min": "00",
            "mon": "06",
            "pretty": "12:00 PM EDT on June 25, 2015",
            "tzname": "America/New_York",
            "year": "2015"
        },
        "fog": "0",
        "gdegreedays": "22",
        "hail": "0",
        "heatingdegreedays": "0",
        "heatingdegreedaysnormal": "1",
        "humidity": "",
        "maxdewpti": "61",
        "maxdewptm": "16",
        "maxhumidity": "76",
        "maxpressurei": "30.03",
        "maxpressurem": "1017",
        "maxtempi": "81",
        "maxtempm": "27",
        "maxvisi": "10",
        "maxvism": "16",
        "maxwspdi": "15",
        "maxwspdm": "24",
        "meandewpti": "55",
        "meandewptm": "13",
        "meanpressurei": "29.98",
        "meanpressurem": "1015",
        "meantempi": "73",
        "meantempm": "23",
        "meanvisi": "10",
        "meanvism": "16",
        "meanwdird": "292",
        "meanwdire": "",
        "meanwindspdi": "7",
        "meanwindspdm": "12",
        "mindewpti": "52",
        "mindewptm": "11",
        "minhumidity": "36",
        "minpressurei": "29.93",
        "minpressurem": "1013",
        "mintempi": "64",
        "mintempm": "18",
        "minvisi": "10",
        "minvism": "16",
        "minwspdi": "0",
        "minwspdm": "0",
        "monthtodatecoolingdegreedays": "93",
        "monthtodatecoolingdegreedaysnormal": "102",
        "monthtodateheatingdegreedays": "86",
        "monthtodateheatingdegreedaysnormal": "53",
        "monthtodatesnowfalli": "0.00",
        "monthtodatesnowfallm": "0.00",
        "precipi": "0.00",
        "precipm": "0.00",
        "precipsource": "",
        "rain": "0",
        "since1jancoolingdegreedays": "154",
        "since1jancoolingdegreedaysnormal": "132",
        "since1julheatingdegreedays": "6017",
        "since1julheatingdegreedaysnormal": "5679",
        "since1julsnowfalli": "110.60",
        "since1julsnowfallm": "280.92",
        "since1sepcoolingdegreedays": "",
        "since1sepcoolingdegreedaysnormal": "",
        "since1sepheatingdegreedays": "",
        "since1sepheatingdegreedaysnormal": "",
        "snow": "0",
        "snowdepthi": "",
        "snowdepthm": "",
        "snowfalli": "0.00",
        "snowfallm": "0.00",
        "thunder": "0",
        "tornado": "0"
    }
]