[
    {
        "coolingdegreedays": "0",
        "coolingdegreedaysnormal": "1",
        "date": {
            "hour": "12",
            "mday": "19",
            "min": "00",
            "mon": "05",
            "pretty": "12:00 PM EDT on May 19, 2015",
            "tzname": "America/New_York",
            "year": "2015"
        },
        "fog": "0",
        "gdegreedays": "6",
        "hail": "0",
        "heatingdegreedays": "6",
        "heatingdegreedaysnormal": "7",
        "humidity": "",
        "maxdewpti": "63",
        "maxdewptm": "17",
        "maxhumidity": "100",
        "maxpressurei": "30.09",
        "maxpressurem": "1019",
        "maxtempi": "65",
        "maxtempm": "18",
        "maxvisi": "10",
        "maxvism": "16",
        "maxwspdi": "16",
        "maxwspdm": "26",
        "meandewpti": "56",
        "meandewptm": "13",
        "meanpressurei": "29.90",
        "meanpressurem": "1012",
        "meantempi": "59",
        "meantempm": "15",
        "meanvisi": "8",
        "meanvism": "13",
        "meanwdird": "203",
        "meanwdire": "",
        "meanwindspdi": "10",
        "meanwindspdm": "16",
        "mindewpti": "48",
        "mindewptm": "9",
        "minhumidity": "83",
        "minpressurei": "29.72",
        "minpressurem": "1006",
        "mintempi": "52",
        "mintempm": "11",
        "minvisi": "2",
        "minvism": "3",
        "minwspdi": "6",
        "minwspdm": "10",
        "monthtodatecoolingdegreedays": "15",
        "monthtodatecoolingdegreedaysnormal": "6",
        "monthtodateheatingdegreedays": "108",
        "monthtodateheatingdegreedaysnormal": "179",
        "monthtodatesnowfalli": "0.00",
        "monthtodatesnowfallm": "0.00",
        "precipi": "0.27",
        "precipm": "6.86",
        "precipsource": "",
        "rain": "1",
        "since1jancoolingdegreedays": "15",
        "since1jancoolingdegreedaysnormal": "9",
        "since1julheatingdegreedays": "5902",
        "since1julheatingdegreedaysnormal": "5560",
        "since1julsnowfalli": "110.60",
        "since1julsnowfallm": "280.92",
        "since1sepcoolingdegreedays": "",
        "since1sepcoolingdegreedaysnormal": "",
        "since1sepheatingdegreedays": "",
        "since1sepheatingdegreedaysnormal": "",
        "snow": "0",
        "snowdepthi": "",
        "snowdepthm": "",
        "snowfalli": "0.00",
        "snowfallm": "0.00",
        "thunder": "0",
        "tornado": "0"
    }
]