[
    {
        "coolingdegreedays": "0",
        "coolingdegreedaysnormal": "1",
        "date": {
            "hour": "12",
            "mday": "17",
            "min": "00",
            "mon": "09",
            "pretty": "12:00 PM PDT on September 17, 2012",
            "tzname": "America/Los_Angeles",
            "year": "2012"
        },
        "fog": "0",
        "gdegreedays": "10",
        "hail": "0",
        "heatingdegreedays": "5",
        "heatingdegreedaysnormal": "2",
        "humidity": "",
        "maxdewpti": "50",
        "maxdewptm": "10",
        "maxhumidity": "83",
        "maxpressurei": "30.07",
        "maxpressurem": "1018",
        "maxtempi": "66",
        "maxtempm": "19",
        "maxvisi": "10",
        "maxvism": "16",
        "maxwspdi": "24",
        "maxwspdm": "39",
        "meandewpti": "48",
        "meandewptm": "9",
        "meanpressurei": "30.04",
        "meanpressurem": "1017",
        "meantempi": "60",
        "meantempm": "16",
        "meanvisi": "10",
        "meanvism": "16",
        "meanwdird": "276",
        "meanwdire": "",
        "meanwindspdi": "10",
        "meanwindspdm": "16",
        "mindewpti": "48",
        "mindewptm": "9",
        "minhumidity": "56",
        "minpressurei": "30.00",
        "minpressurem": "1016",
        "mintempi": "54",
        "mintempm": "12",
        "minvisi": "10",
        "minvism": "16",
        "minwspdi": "0",
        "minwspdm": "0",
        "monthtodatecoolingdegreedays": "0",
        "monthtodatecoolingdegreedaysnormal": "32",
        "monthtodateheatingdegreedays": "70",
        "monthtodateheatingdegreedaysnormal": "34",
        "monthtodatesnowfalli": "0.00",
        "monthtodatesnowfallm": "0.00",
        "precipi": "0.00",
        "precipm": "0.00",
        "precipsource": "",
        "rain": "0",
        "since1jancoolingdegreedays": "34",
        "since1jancoolingdegreedaysnormal": "129",
        "since1julheatingdegreedays": "250",
        "since1julheatingdegreedaysnormal": "147",
        "since1julsnowfalli": "0.00",
        "since1julsnowfallm": "0.00",
        "since1sepcoolingdegreedays": "0",
        "since1sepcoolingdegreedaysnormal": "32",
        "since1sepheatingdegreedays": "70",
        "since1sepheatingdegreedaysnormal": "34",
        "snow": "0",
        "snowdepthi": "",
        "snowdepthm": "",
        "snowfalli": "0.00",
        "snowfallm": "0.00",
        "thunder": "0",
        "tornado": "0"
    }
]