[
    {
        "coolingdegreedays": "0",
        "coolingdegreedaysnormal": "1",
        "date": {
            "hour": "12",
            "mday": "24",
            "min": "00",
            "mon": "08",
            "pretty": "12:00 PM PDT on August 24, 2012",
            "tzname": "America/Los_Angeles",
            "year": "2012"
        },
        "fog": "0",
        "gdegreedays": "12",
        "hail": "0",
        "heatingdegreedays": "3",
        "heatingdegreedaysnormal": "1",
        "humidity": "",
        "maxdewpti": "55",
        "maxdewptm": "13",
        "maxhumidity": "86",
        "maxpressurei": "29.91",
        "maxpressurem": "1013",
        "maxtempi": "71",
        "maxtempm": "22",
        "maxvisi": "10",
        "maxvism": "16",
        "maxwspdi": "25",
        "maxwspdm": "40",
        "meandewpti": "51",
        "meandewptm": "11",
        "meanpressurei": "29.88",
        "meanpressurem": "1012",
        "meantempi": "62",
        "meantempm": "17",
        "meanvisi": "10",
        "meanvism": "16",
        "meanwdird": "310",
        "meanwdire": "",
        "meanwindspdi": "9",
        "meanwindspdm": "15",
        "mindewpti": "48",
        "mindewptm": "9",
        "minhumidity": "53",
        "minpressurei": "29.84",
        "minpressurem": "1010",
        "mintempi": "53",
        "mintempm": "12",
        "minvisi": "9",
        "minvism": "14",
        "minwspdi": "0",
        "minwspdm": "0",
        "monthtodatecoolingdegreedays": "0",
        "monthtodatecoolingdegreedaysnormal": "24",
        "monthtodateheatingdegreedays": "85",
        "monthtodateheatingdegreedaysnormal": "35",
        "monthtodatesnowfalli": "0.00",
        "monthtodatesnowfallm": "0.00",
        "precipi": "0.00",
        "precipm": "0.00",
        "precipsource": "",
        "rain": "0",
        "since1jancoolingdegreedays": "28",
        "since1jancoolingdegreedaysnormal": "88",
        "since1julheatingdegreedays": "163",
        "since1julheatingdegreedaysnormal": "100",
        "since1julsnowfalli": "0.00",
        "since1julsnowfallm": "0.00",
        "since1sepcoolingdegreedays": "",
        "since1sepcoolingdegreedaysnormal": "",
        "since1sepheatingdegreedays": "",
        "since1sepheatingdegreedaysnormal": "",
        "snow": "0",
        "snowdepthi": "",
        "snowdepthm": "",
        "snowfalli": "0.00",
        "snowfallm": "0.00",
        "thunder": "0",
        "tornado": "0"
    }
]