[
    {
        "coolingdegreedays": "0",
        "coolingdegreedaysnormal": "0",
        "date": {
            "hour": "12",
            "mday": "03",
            "min": "00",
            "mon": "03",
            "pretty": "12:00 PM EST on March 03, 2015",
            "tzname": "America/New_York",
            "year": "2015"
        },
        "fog": "0",
        "gdegreedays": "0",
        "hail": "0",
        "heatingdegreedays": "38",
        "heatingdegreedaysnormal": "30",
        "humidity": "",
        "maxdewpti": "31",
        "maxdewptm": "-1",
        "maxhumidity": "92",
        "maxpressurei": "30.41",
        "maxpressurem": "1030",
        "maxtempi": "33",
        "maxtempm": "1",
        "maxvisi": "10",
        "maxvism": "16",
        "maxwspdi": "24",
        "maxwspdm": "39",
        "meandewpti": "14",
        "meandewptm": "-10",
        "meanpressurei": "30.17",
        "meanpressurem": "1022",
        "meantempi": "27",
        "meantempm": "-3",
        "meanvisi": "6",
        "meanvism": "10",
        "meanwdird": "213",
        "meanwdire": "",
        "meanwindspdi": "10",
        "meanwindspdm": "16",
        "mindewpti": "1",
        "mindewptm": "-17",
        "minhumidity": "28",
        "minpressurei": "29.80",
        "minpressurem": "1009",
        "mintempi": "20",
        "mintempm": "-7",
        "minvisi": "1",
        "minvism": "1",
        "minwspdi": "0",
        "minwspdm": "0",
        "monthtodatecoolingdegreedays": "0",
        "monthtodatecoolingdegreedaysnormal": "0",
        "monthtodateheatingdegreedays": "115",
        "monthtodateheatingdegreedaysnormal": "91",
        "monthtodatesnowfalli": "3.70",
        "monthtodatesnowfallm": "9.40",
        "precipi": "0.26",
        "precipm": "6.60",
        "precipsource": "",
        "rain": "1",
        "since1jancoolingdegreedays": "0",
        "since1jancoolingdegreedaysnormal": "0",
        "since1julheatingdegreedays": "4430",
        "since1julheatingdegreedaysnormal": "4133",
        "since1julsnowfalli": "105.70",
        "since1julsnowfallm": "268.48",
        "since1sepcoolingdegreedays": "",
        "since1sepcoolingdegreedaysnormal": "",
        "since1sepheatingdegreedays": "",
        "since1sepheatingdegreedaysnormal": "",
        "snow": "1",
        "snowdepthi": "",
        "snowdepthm": "",
        "snowfalli": "1.60",
        "snowfallm": "4.06",
        "thunder": "0",
        "tornado": "0"
    }
]