[
    {
        "coolingdegreedays": "16",
        "coolingdegreedaysnormal": "",
        "date": {
            "hour": "12",
            "mday": "27",
            "min": "00",
            "mon": "09",
            "pretty": "12:00 PM EDT on September 27, 2016",
            "tzname": "America/New_York",
            "year": "2016"
        },
        "fog": "0",
        "gdegreedays": "30",
        "hail": "0",
        "heatingdegreedays": "0",
        "heatingdegreedaysnormal": "",
        "humidity": "",
        "maxdewpti": "74",
        "maxdewptm": "23",
        "maxhumidity": "97",
        "maxpressurei": "29.99",
        "maxpressurem": "1015",
        "maxtempi": "91",
        "maxtempm": "33",
        "maxvisi": "10",
        "maxvism": "16",
        "maxwspdi": "14",
        "maxwspdm": "23",
        "meandewpti": "70",
        "meandewptm": "21",
        "meanpressurei": "29.94",
        "meanpressurem": "1014",
        "meantempi": "80",
        "meantempm": "27",
        "meanvisi": "10",
        "meanvism": "16",
        "meanwdird": "236",
        "meanwdire": "",
        "meanwindspdi": "5",
        "meanwindspdm": "8",
        "mindewpti": "66",
        "mindewptm": "19",
        "minhumidity": "46",
        "minpressurei": "29.89",
        "minpressurem": "1012",
        "mintempi": "71",
        "mintempm": "22",
        "minvisi": "9",
        "minvism": "14",
        "minwspdi": "0",
        "minwspdm": "0",
        "monthtodatecoolingdegreedays": "",
        "monthtodatecoolingdegreedaysnormal": "",
        "monthtodateheatingdegreedays": "",
        "monthtodateheatingdegreedaysnormal": "",
        "monthtodatesnowfalli": "",
        "monthtodatesnowfallm": "",
        "precipi": "0.00",
        "precipm": "0.00",
        "precipsource": "",
        "rain": "0",
        "since1jancoolingdegreedays": "",
        "since1jancoolingdegreedaysnormal": "",
        "since1julheatingdegreedays": "",
        "since1julheatingdegreedaysnormal": "",
        "since1julsnowfalli": "",
        "since1julsnowfallm": "",
        "since1sepcoolingdegreedays": "",
        "since1sepcoolingdegreedaysnormal": "",
        "since1sepheatingdegreedays": "",
        "since1sepheatingdegreedaysnormal": "",
        "snow": "0",
        "snowdepthi": "",
        "snowdepthm": "",
        "snowfalli": "0.00",
        "snowfallm": "0.00",
        "thunder": "1",
        "tornado": "0"
    }
]