[
    {
        "coolingdegreedays": "6",
        "coolingdegreedaysnormal": "0",
        "date": {
            "hour": "12",
            "mday": "11",
            "min": "00",
            "mon": "05",
            "pretty": "12:00 PM EDT on May 11, 2014",
            "tzname": "America/New_York",
            "year": "2014"
        },
        "fog": "0",
        "gdegreedays": "21",
        "hail": "0",
        "heatingdegreedays": "0",
        "heatingdegreedaysnormal": "9",
        "humidity": "",
        "maxdewpti": "58",
        "maxdewptm": "14",
        "maxhumidity": "78",
        "maxpressurei": "30.02",
        "maxpressurem": "1016",
        "maxtempi": "80",
        "maxtempm": "27",
        "maxvisi": "10",
        "maxvism": "16",
        "maxwspdi": "22",
        "maxwspdm": "35",
        "meandewpti": "38",
        "meandewptm": "3",
        "meanpressurei": "29.91",
        "meanpressurem": "1013",
        "meantempi": "71",
        "meantempm": "22",
        "meanvisi": "10",
        "meanvism": "16",
        "meanwdird": "276",
        "meanwdire": "",
        "meanwindspdi": "12",
        "meanwindspdm": "19",
        "mindewpti": "27",
        "mindewptm": "-3",
        "minhumidity": "14",
        "minpressurei": "29.79",
        "minpressurem": "1009",
        "mintempi": "62",
        "mintempm": "17",
        "minvisi": "9",
        "minvism": "14",
        "minwspdi": "8",
        "minwspdm": "13",
        "monthtodatecoolingdegreedays": "10",
        "monthtodatecoolingdegreedaysnormal": "0",
        "monthtodateheatingdegreedays": "76",
        "monthtodateheatingdegreedaysnormal": "116",
        "monthtodatesnowfalli": "0.00",
        "monthtodatesnowfallm": "0.00",
        "precipi": "T",
        "precipm": "T",
        "precipsource": "",
        "rain": "1",
        "since1jancoolingdegreedays": "11",
        "since1jancoolingdegreedaysnormal": "3",
        "since1julheatingdegreedays": "5695",
        "since1julheatingdegreedaysnormal": "5497",
        "since1julsnowfalli": "58.90",
        "since1julsnowfallm": "149.61",
        "since1sepcoolingdegreedays": "",
        "since1sepcoolingdegreedaysnormal": "",
        "since1sepheatingdegreedays": "",
        "since1sepheatingdegreedaysnormal": "",
        "snow": "0",
        "snowdepthi": "",
        "snowdepthm": "",
        "snowfalli": "0.00",
        "snowfallm": "0.00",
        "thunder": "0",
        "tornado": "0"
    }
]