[
    {
        "coolingdegreedays": "0",
        "coolingdegreedaysnormal": "0",
        "date": {
            "hour": "12",
            "mday": "24",
            "min": "00",
            "mon": "12",
            "pretty": "12:00 PM EST on December 24, 2012",
            "tzname": "America/New_York",
            "year": "2012"
        },
        "fog": "0",
        "gdegreedays": "0",
        "hail": "0",
        "heatingdegreedays": "28",
        "heatingdegreedaysnormal": "30",
        "humidity": "",
        "maxdewpti": "34",
        "maxdewptm": "1",
        "maxhumidity": "100",
        "maxpressurei": "30.09",
        "maxpressurem": "1019",
        "maxtempi": "40",
        "maxtempm": "4",
        "maxvisi": "10",
        "maxvism": "16",
        "maxwspdi": "12",
        "maxwspdm": "19",
        "meandewpti": "24",
        "meandewptm": "-4",
        "meanpressurei": "30.02",
        "meanpressurem": "1016",
        "meantempi": "37",
        "meantempm": "3",
        "meanvisi": "8",
        "meanvism": "12",
        "meanwdird": "336",
        "meanwdire": "",
        "meanwindspdi": "4",
        "meanwindspdm": "6",
        "mindewpti": "18",
        "mindewptm": "-8",
        "minhumidity": "47",
        "minpressurei": "29.94",
        "minpressurem": "1014",
        "mintempi": "33",
        "mintempm": "1",
        "minvisi": "2",
        "minvism": "4",
        "minwspdi": "0",
        "minwspdm": "0",
        "monthtodatecoolingdegreedays": "0",
        "monthtodatecoolingdegreedaysnormal": "0",
        "monthtodateheatingdegreedays": "500",
        "monthtodateheatingdegreedaysnormal": "635",
        "monthtodatesnowfalli": "T",
        "monthtodatesnowfallm": "T",
        "precipi": "0.07",
        "precipm": "1.78",
        "precipsource": "",
        "rain": "0",
        "since1jancoolingdegreedays": "1277",
        "since1jancoolingdegreedaysnormal": "1105",
        "since1julheatingdegreedays": "1371",
        "since1julheatingdegreedaysnormal": "1468",
        "since1julsnowfalli": "4.70",
        "since1julsnowfallm": "11.94",
        "since1sepcoolingdegreedays": "",
        "since1sepcoolingdegreedaysnormal": "",
        "since1sepheatingdegreedays": "",
        "since1sepheatingdegreedaysnormal": "",
        "snow": "1",
        "snowdepthi": "0.00",
        "snowdepthm": "0.00",
        "snowfalli": "T",
        "snowfallm": "T",
        "thunder": "0",
        "tornado": "0"
    }
]