[
    {
        "coolingdegreedays": "10",
        "coolingdegreedaysnormal": "7",
        "date": {
            "hour": "12",
            "mday": "03",
            "min": "00",
            "mon": "09",
            "pretty": "12:00 PM EDT on September 03, 2012",
            "tzname": "America/New_York",
            "year": "2012"
        },
        "fog": "0",
        "gdegreedays": "25",
        "hail": "0",
        "heatingdegreedays": "0",
        "heatingdegreedaysnormal": "0",
        "humidity": "",
        "maxdewpti": "70",
        "maxdewptm": "21",
        "maxhumidity": "90",
        "maxpressurei": "30.18",
        "maxpressurem": "1022",
        "maxtempi": "79",
        "maxtempm": "26",
        "maxvisi": "10",
        "maxvism": "16",
        "maxwspdi": "12",
        "maxwspdm": "19",
        "meandewpti": "65",
        "meandewptm": "18",
        "meanpressurei": "30.12",
        "meanpressurem": "1020",
        "meantempi": "75",
        "meantempm": "24",
        "meanvisi": "10",
        "meanvism": "16",
        "meanwdird": "122",
        "meanwdire": "",
        "meanwindspdi": "7",
        "meanwindspdm": "11",
        "mindewpti": "58",
        "mindewptm": "14",
        "minhumidity": "48",
        "minpressurei": "30.08",
        "minpressurem": "1019",
        "mintempi": "71",
        "mintempm": "22",
        "minvisi": "10",
        "minvism": "16",
        "minwspdi": "0",
        "minwspdm": "0",
        "monthtodatecoolingdegreedays": "40",
        "monthtodatecoolingdegreedaysnormal": "23",
        "monthtodateheatingdegreedays": "0",
        "monthtodateheatingdegreedaysnormal": "0",
        "monthtodatesnowfalli": "0.00",
        "monthtodatesnowfallm": "0.00",
        "precipi": "T",
        "precipm": "T",
        "precipsource": "",
        "rain": "0",
        "since1jancoolingdegreedays": "1158",
        "since1jancoolingdegreedaysnormal": "977",
        "since1julheatingdegreedays": "0",
        "since1julheatingdegreedaysnormal": "2",
        "since1julsnowfalli": "0.00",
        "since1julsnowfallm": "0.00",
        "since1sepcoolingdegreedays": "40",
        "since1sepcoolingdegreedaysnormal": "23",
        "since1sepheatingdegreedays": "0",
        "since1sepheatingdegreedaysnormal": "0",
        "snow": "0",
        "snowdepthi": "0.00",
        "snowdepthm": "0.00",
        "snowfalli": "0.00",
        "snowfallm": "0.00",
        "thunder": "0",
        "tornado": "0"
    }
]