[
    {
        "coolingdegreedays": "0",
        "coolingdegreedaysnormal": "2",
        "date": {
            "hour": "12",
            "mday": "29",
            "min": "00",
            "mon": "09",
            "pretty": "12:00 PM EDT on September 29, 2016",
            "tzname": "America/New_York",
            "year": "2016"
        },
        "fog": "0",
        "gdegreedays": "10",
        "hail": "0",
        "heatingdegreedays": "4",
        "heatingdegreedaysnormal": "4",
        "humidity": "",
        "maxdewpti": "55",
        "maxdewptm": "13",
        "maxhumidity": "87",
        "maxpressurei": "30.38",
        "maxpressurem": "1029",
        "maxtempi": "64",
        "maxtempm": "18",
        "maxvisi": "10",
        "maxvism": "16",
        "maxwspdi": "21",
        "maxwspdm": "34",
        "meandewpti": "53",
        "meandewptm": "12",
        "meanpressurei": "30.33",
        "meanpressurem": "1027",
        "meantempi": "61",
        "meantempm": "16",
        "meanvisi": "9",
        "meanvism": "15",
        "meanwdird": "77",
        "meanwdire": "",
        "meanwindspdi": "11",
        "meanwindspdm": "18",
        "mindewpti": "51",
        "mindewptm": "11",
        "minhumidity": "63",
        "minpressurei": "30.25",
        "minpressurem": "1024",
        "mintempi": "57",
        "mintempm": "14",
        "minvisi": "3",
        "minvism": "5",
        "minwspdi": "7",
        "minwspdm": "11",
        "monthtodatecoolingdegreedays": "228",
        "monthtodatecoolingdegreedaysnormal": "131",
        "monthtodateheatingdegreedays": "10",
        "monthtodateheatingdegreedaysnormal": "38",
        "monthtodatesnowfalli": "0.00",
        "monthtodatesnowfallm": "0.00",
        "precipi": "0.00",
        "precipm": "0.00",
        "precipsource": "",
        "rain": "0",
        "since1jancoolingdegreedays": "1460",
        "since1jancoolingdegreedaysnormal": "1085",
        "since1julheatingdegreedays": "10",
        "since1julheatingdegreedaysnormal": "40",
        "since1julsnowfalli": "0.00",
        "since1julsnowfallm": "0.00",
        "since1sepcoolingdegreedays": "228",
        "since1sepcoolingdegreedaysnormal": "131",
        "since1sepheatingdegreedays": "10",
        "since1sepheatingdegreedaysnormal": "38",
        "snow": "0",
        "snowdepthi": "0.00",
        "snowdepthm": "0.00",
        "snowfalli": "0.00",
        "snowfallm": "0.00",
        "thunder": "0",
        "tornado": "0"
    }
]