[
    {
        "coolingdegreedays": "12",
        "coolingdegreedaysnormal": "10",
        "date": {
            "hour": "12",
            "mday": "23",
            "min": "00",
            "mon": "08",
            "pretty": "12:00 PM EDT on August 23, 2012",
            "tzname": "America/New_York",
            "year": "2012"
        },
        "fog": "0",
        "gdegreedays": "26",
        "hail": "0",
        "heatingdegreedays": "0",
        "heatingdegreedaysnormal": "0",
        "humidity": "",
        "maxdewpti": "64",
        "maxdewptm": "18",
        "maxhumidity": "84",
        "maxpressurei": "30.17",
        "maxpressurem": "1022",
        "maxtempi": "85",
        "maxtempm": "29",
        "maxvisi": "10",
        "maxvism": "16",
        "maxwspdi": "9",
        "maxwspdm": "14",
        "meandewpti": "62",
        "meandewptm": "17",
        "meanpressurei": "30.14",
        "meanpressurem": "1021",
        "meantempi": "77",
        "meantempm": "25",
        "meanvisi": "10",
        "meanvism": "15",
        "meanwdird": "253",
        "meanwdire": "",
        "meanwindspdi": "2",
        "meanwindspdm": "3",
        "mindewpti": "56",
        "mindewptm": "13",
        "minhumidity": "40",
        "minpressurei": "30.10",
        "minpressurem": "1019",
        "mintempi": "69",
        "mintempm": "21",
        "minvisi": "8",
        "minvism": "13",
        "minwspdi": "0",
        "minwspdm": "0",
        "monthtodatecoolingdegreedays": "276",
        "monthtodatecoolingdegreedaysnormal": "246",
        "monthtodateheatingdegreedays": "0",
        "monthtodateheatingdegreedaysnormal": "0",
        "monthtodatesnowfalli": "0.00",
        "monthtodatesnowfallm": "0.00",
        "precipi": "0.00",
        "precipm": "0.00",
        "precipsource": "",
        "rain": "0",
        "since1jancoolingdegreedays": "1025",
        "since1jancoolingdegreedaysnormal": "882",
        "since1julheatingdegreedays": "0",
        "since1julheatingdegreedaysnormal": "0",
        "since1julsnowfalli": "0.00",
        "since1julsnowfallm": "0.00",
        "since1sepcoolingdegreedays": "",
        "since1sepcoolingdegreedaysnormal": "",
        "since1sepheatingdegreedays": "",
        "since1sepheatingdegreedaysnormal": "",
        "snow": "0",
        "snowdepthi": "0.00",
        "snowdepthm": "0.00",
        "snowfalli": "0.00",
        "snowfallm": "0.00",
        "thunder": "0",
        "tornado": "0"
    }
]