[
    {
        "coolingdegreedays": "0",
        "coolingdegreedaysnormal": "0",
        "date": {
            "hour": "12",
            "mday": "11",
            "min": "00",
            "mon": "11",
            "pretty": "12:00 PM EST on November 11, 2012",
            "tzname": "America/New_York",
            "year": "2012"
        },
        "fog": "0",
        "gdegreedays": "6",
        "hail": "0",
        "heatingdegreedays": "8",
        "heatingdegreedaysnormal": "16",
        "humidity": "",
        "maxdewpti": "50",
        "maxdewptm": "10",
        "maxhumidity": "86",
        "maxpressurei": "30.49",
        "maxpressurem": "1032",
        "maxtempi": "64",
        "maxtempm": "18",
        "maxvisi": "10",
        "maxvism": "16",
        "maxwspdi": "8",
        "maxwspdm": "13",
        "meandewpti": "46",
        "meandewptm": "8",
        "meanpressurei": "30.46",
        "meanpressurem": "1031",
        "meantempi": "57",
        "meantempm": "14",
        "meanvisi": "8",
        "meanvism": "12",
        "meanwdird": "170",
        "meanwdire": "",
        "meanwindspdi": "3",
        "meanwindspdm": "4",
        "mindewpti": "40",
        "mindewptm": "4",
        "minhumidity": "56",
        "minpressurei": "30.42",
        "minpressurem": "1030",
        "mintempi": "50",
        "mintempm": "10",
        "minvisi": "4",
        "minvism": "6",
        "minwspdi": "0",
        "minwspdm": "0",
        "monthtodatecoolingdegreedays": "0",
        "monthtodatecoolingdegreedaysnormal": "0",
        "monthtodateheatingdegreedays": "225",
        "monthtodateheatingdegreedaysnormal": "158",
        "monthtodatesnowfalli": "4.70",
        "monthtodatesnowfallm": "11.94",
        "precipi": "0.00",
        "precipm": "0.00",
        "precipsource": "",
        "rain": "0",
        "since1jancoolingdegreedays": "1277",
        "since1jancoolingdegreedaysnormal": "1104",
        "since1julheatingdegreedays": "469",
        "since1julheatingdegreedaysnormal": "471",
        "since1julsnowfalli": "4.70",
        "since1julsnowfallm": "11.94",
        "since1sepcoolingdegreedays": "159",
        "since1sepcoolingdegreedaysnormal": "150",
        "since1sepheatingdegreedays": "469",
        "since1sepheatingdegreedaysnormal": "469",
        "snow": "0",
        "snowdepthi": "0.00",
        "snowdepthm": "0.00",
        "snowfalli": "0.00",
        "snowfallm": "0.00",
        "thunder": "0",
        "tornado": "0"
    }
]