[
    {
        "coolingdegreedays": "5",
        "coolingdegreedaysnormal": "2",
        "date": {
            "hour": "12",
            "mday": "16",
            "min": "00",
            "mon": "05",
            "pretty": "12:00 PM EDT on May 16, 2012",
            "tzname": "America/New_York",
            "year": "2012"
        },
        "fog": "1",
        "gdegreedays": "20",
        "hail": "0",
        "heatingdegreedays": "0",
        "heatingdegreedaysnormal": "4",
        "humidity": "",
        "maxdewpti": "67",
        "maxdewptm": "19",
        "maxhumidity": "100",
        "maxpressurei": "29.98",
        "maxpressurem": "1015",
        "maxtempi": "78",
        "maxtempm": "26",
        "maxvisi": "10",
        "maxvism": "16",
        "maxwspdi": "9",
        "maxwspdm": "14",
        "meandewpti": "63",
        "meandewptm": "17",
        "meanpressurei": "29.91",
        "meanpressurem": "1013",
        "meantempi": "70",
        "meantempm": "21",
        "meanvisi": "4",
        "meanvism": "6",
        "meanwdird": "124",
        "meanwdire": "",
        "meanwindspdi": "2",
        "meanwindspdm": "3",
        "mindewpti": "56",
        "mindewptm": "13",
        "minhumidity": "57",
        "minpressurei": "29.83",
        "minpressurem": "1010",
        "mintempi": "61",
        "mintempm": "16",
        "minvisi": "0",
        "minvism": "1",
        "minwspdi": "0",
        "minwspdm": "0",
        "monthtodatecoolingdegreedays": "15",
        "monthtodatecoolingdegreedaysnormal": "18",
        "monthtodateheatingdegreedays": "68",
        "monthtodateheatingdegreedaysnormal": "93",
        "monthtodatesnowfalli": "0.00",
        "monthtodatesnowfallm": "0.00",
        "precipi": "0.09",
        "precipm": "2.29",
        "precipsource": "",
        "rain": "1",
        "since1jancoolingdegreedays": "39",
        "since1jancoolingdegreedaysnormal": "30",
        "since1julheatingdegreedays": "3690",
        "since1julheatingdegreedaysnormal": "4686",
        "since1julsnowfalli": "7.40",
        "since1julsnowfallm": "18.80",
        "since1sepcoolingdegreedays": "",
        "since1sepcoolingdegreedaysnormal": "",
        "since1sepheatingdegreedays": "",
        "since1sepheatingdegreedaysnormal": "",
        "snow": "0",
        "snowdepthi": "0.00",
        "snowdepthm": "0.00",
        "snowfalli": "0.00",
        "snowfallm": "0.00",
        "thunder": "0",
        "tornado": "0"
    }
]