[
    {
        "coolingdegreedays": "0",
        "coolingdegreedaysnormal": "0",
        "date": {
            "hour": "12",
            "mday": "01",
            "min": "00",
            "mon": "12",
            "pretty": "12:00 PM EST on December 01, 2012",
            "tzname": "America/New_York",
            "year": "2012"
        },
        "fog": "0",
        "gdegreedays": "0",
        "hail": "0",
        "heatingdegreedays": "35",
        "heatingdegreedaysnormal": "25",
        "humidity": "",
        "maxdewpti": "29",
        "maxdewptm": "-2",
        "maxhumidity": "92",
        "maxpressurei": "30.64",
        "maxpressurem": "1037",
        "maxtempi": "32",
        "maxtempm": "0",
        "maxvisi": "10",
        "maxvism": "16",
        "maxwspdi": "13",
        "maxwspdm": "21",
        "meandewpti": "23",
        "meandewptm": "-5",
        "meanpressurei": "30.58",
        "meanpressurem": "1035",
        "meantempi": "30",
        "meantempm": "-1",
        "meanvisi": "6",
        "meanvism": "10",
        "meanwdird": "342",
        "meanwdire": "",
        "meanwindspdi": "7",
        "meanwindspdm": "10",
        "mindewpti": "13",
        "mindewptm": "-11",
        "minhumidity": "45",
        "minpressurei": "30.51",
        "minpressurem": "1033",
        "mintempi": "28",
        "mintempm": "-2",
        "minvisi": "1",
        "minvism": "1",
        "minwspdi": "4",
        "minwspdm": "6",
        "monthtodatecoolingdegreedays": "0",
        "monthtodatecoolingdegreedaysnormal": "0",
        "monthtodateheatingdegreedays": "35",
        "monthtodateheatingdegreedaysnormal": "25",
        "monthtodatesnowfalli": "0.50",
        "monthtodatesnowfallm": "1.27",
        "precipi": "0.03",
        "precipm": "0.76",
        "precipsource": "",
        "rain": "0",
        "since1jancoolingdegreedays": "905",
        "since1jancoolingdegreedaysnormal": "747",
        "since1julheatingdegreedays": "1048",
        "since1julheatingdegreedaysnormal": "1080",
        "since1julsnowfalli": "0.90",
        "since1julsnowfallm": "2.29",
        "since1sepcoolingdegreedays": "",
        "since1sepcoolingdegreedaysnormal": "",
        "since1sepheatingdegreedays": "",
        "since1sepheatingdegreedaysnormal": "",
        "snow": "1",
        "snowdepthi": "",
        "snowdepthm": "",
        "snowfalli": "0.50",
        "snowfallm": "1.27",
        "thunder": "0",
        "tornado": "0"
    }
]