[
    {
        "coolingdegreedays": "4",
        "coolingdegreedaysnormal": "1",
        "date": {
            "hour": "12",
            "mday": "26",
            "min": "00",
            "mon": "05",
            "pretty": "12:00 PM EDT on May 26, 2016",
            "tzname": "America/New_York",
            "year": "2016"
        },
        "fog": "0",
        "gdegreedays": "20",
        "hail": "0",
        "heatingdegreedays": "0",
        "heatingdegreedaysnormal": "5",
        "humidity": "",
        "maxdewpti": "59",
        "maxdewptm": "15",
        "maxhumidity": "87",
        "maxpressurei": "30.11",
        "maxpressurem": "1020",
        "maxtempi": "79",
        "maxtempm": "26",
        "maxvisi": "10",
        "maxvism": "16",
        "maxwspdi": "20",
        "maxwspdm": "32",
        "meandewpti": "55",
        "meandewptm": "13",
        "meanpressurei": "30.06",
        "meanpressurem": "1018",
        "meantempi": "69",
        "meantempm": "21",
        "meanvisi": "10",
        "meanvism": "16",
        "meanwdird": "62",
        "meanwdire": "",
        "meanwindspdi": "8",
        "meanwindspdm": "13",
        "mindewpti": "52",
        "mindewptm": "11",
        "minhumidity": "46",
        "minpressurei": "30.00",
        "minpressurem": "1016",
        "mintempi": "58",
        "mintempm": "14",
        "minvisi": "9",
        "minvism": "14",
        "minwspdi": "0",
        "minwspdm": "0",
        "monthtodatecoolingdegreedays": "13",
        "monthtodatecoolingdegreedaysnormal": "13",
        "monthtodateheatingdegreedays": "233",
        "monthtodateheatingdegreedaysnormal": "222",
        "monthtodatesnowfalli": "0.00",
        "monthtodatesnowfallm": "0.00",
        "precipi": "0.00",
        "precipm": "0.00",
        "precipsource": "",
        "rain": "0",
        "since1jancoolingdegreedays": "16",
        "since1jancoolingdegreedaysnormal": "16",
        "since1julheatingdegreedays": "4786",
        "since1julheatingdegreedaysnormal": "5603",
        "since1julsnowfalli": "36.10",
        "since1julsnowfallm": "91.69",
        "since1sepcoolingdegreedays": "",
        "since1sepcoolingdegreedaysnormal": "",
        "since1sepheatingdegreedays": "",
        "since1sepheatingdegreedaysnormal": "",
        "snow": "0",
        "snowdepthi": "",
        "snowdepthm": "",
        "snowfalli": "0.00",
        "snowfallm": "0.00",
        "thunder": "0",
        "tornado": "0"
    }
]