[
    {
        "coolingdegreedays": "0",
        "coolingdegreedaysnormal": "2",
        "date": {
            "hour": "12",
            "mday": "17",
            "min": "00",
            "mon": "05",
            "pretty": "12:00 PM EDT on May 17, 2016",
            "tzname": "America/New_York",
            "year": "2016"
        },
        "fog": "0",
        "gdegreedays": "10",
        "hail": "0",
        "heatingdegreedays": "7",
        "heatingdegreedaysnormal": "4",
        "humidity": "",
        "maxdewpti": "48",
        "maxdewptm": "9",
        "maxhumidity": "72",
        "maxpressurei": "30.18",
        "maxpressurem": "1022",
        "maxtempi": "64",
        "maxtempm": "18",
        "maxvisi": "10",
        "maxvism": "16",
        "maxwspdi": "6",
        "maxwspdm": "10",
        "meandewpti": "40",
        "meandewptm": "4",
        "meanpressurei": "30.15",
        "meanpressurem": "1021",
        "meantempi": "58",
        "meantempm": "14",
        "meanvisi": "10",
        "meanvism": "16",
        "meanwdird": "-1",
        "meanwdire": "",
        "meanwindspdi": "4",
        "meanwindspdm": "6",
        "mindewpti": "33",
        "mindewptm": "1",
        "minhumidity": "40",
        "minpressurei": "30.12",
        "minpressurem": "1020",
        "mintempi": "52",
        "mintempm": "11",
        "minvisi": "9",
        "minvism": "14",
        "minwspdi": "0",
        "minwspdm": "0",
        "monthtodatecoolingdegreedays": "3",
        "monthtodatecoolingdegreedaysnormal": "20",
        "monthtodateheatingdegreedays": "146",
        "monthtodateheatingdegreedaysnormal": "97",
        "monthtodatesnowfalli": "0.00",
        "monthtodatesnowfallm": "0.00",
        "precipi": "T",
        "precipm": "T",
        "precipsource": "",
        "rain": "0",
        "since1jancoolingdegreedays": "22",
        "since1jancoolingdegreedaysnormal": "32",
        "since1julheatingdegreedays": "3746",
        "since1julheatingdegreedaysnormal": "4690",
        "since1julsnowfalli": "32.80",
        "since1julsnowfallm": "83.31",
        "since1sepcoolingdegreedays": "",
        "since1sepcoolingdegreedaysnormal": "",
        "since1sepheatingdegreedays": "",
        "since1sepheatingdegreedaysnormal": "",
        "snow": "0",
        "snowdepthi": "0.00",
        "snowdepthm": "0.00",
        "snowfalli": "0.00",
        "snowfallm": "0.00",
        "thunder": "0",
        "tornado": "0"
    }
]